khmerphonemizer/__init__.py
khmerphonemizer/g2p.fst
khmerphonemizer/km_lexicon.tsv
khmerphonemizer-0.0.3.dist-info/LICENSE
khmerphonemizer-0.0.3.dist-info/METADATA
khmerphonemizer-0.0.3.dist-info/WHEEL
khmerphonemizer-0.0.3.dist-info/top_level.txt
khmerphonemizer-0.0.3.dist-info/RECORD
