Metadata-Version: 2.1
Name: khmerphonemizer
Version: 0.0.3
Summary: A Free, Standalone and Open-Source Khmer Grapheme-to-Phonemes.
Author-email: Seanghay Yath <seanghay.dev@gmail.com>
Project-URL: repository, https://github.com/seanghay/khmerphonemizer
Classifier: Development Status :: 5 - Production/Stable
Classifier: License :: OSI Approved :: MIT License
Classifier: Operating System :: OS Independent
Classifier: Programming Language :: Python :: 3
Classifier: Programming Language :: Cython
Classifier: Topic :: Scientific/Engineering :: Artificial Intelligence
Requires-Python: >=3.7
License-File: LICENSE
Requires-Dist: khmercut
Requires-Dist: sosap
